liebre/__init__.py
liebre/consumer.py
liebre/errors.py
liebre/liebre.py
liebre/logger.py
liebre/message.py
liebre/producer.py
liebre/rabbit_store.py
liebre/utils.py
liebre-2.2508.1.dist-info/licenses/LICENSE
liebre-2.2508.1.dist-info/METADATA
liebre-2.2508.1.dist-info/WHEEL
liebre-2.2508.1.dist-info/top_level.txt
liebre-2.2508.1.dist-info/RECORD
